setup.cfg
setup.py
box_it_up/__init__.py
box_it_up/box_it_up.py
box_it_up.egg-info/PKG-INFO
box_it_up.egg-info/SOURCES.txt
box_it_up.egg-info/dependency_links.txt
box_it_up.egg-info/top_level.txt