Metadata-Version: 1.1
Name: box-it-up
Version: 0.0.3
Summary: Python class for formatting various kinds of table data into an ascii table.
Home-page: https://github.com/rpappalax/box-it-up
Author: Richard Pappalardo
Author-email: rpappalax@gmail.com
License: UNKNOWN
Keywords: testing,logging,reporting,stats,table
Platform: UNKNOWN
Classifier: Programming Language :: Python
Classifier: Programming Language :: Python :: 2
Classifier: Programming Language :: Python :: 2.6
Classifier: Programming Language :: Python :: 2.7
Classifier: Programming Language :: Python :: 3
Classifier: Programming Language :: Python :: 3.2
Classifier: Programming Language :: Python :: 3.3
